[
  {
    "id": 1,
    "name": "Сергій",
    "position": "Керівник організації",
    "picture": "./images/sergiy-b.png",
    "indexId": 1
  },
  {
    "id": 2,
    "name": "Ярослав",
    "position": "Проєктний менеджер",
    "picture": "./images/yaroslav.png",
    "indexId": 2
  },
  {
    "id": 3,
    "name": "Сергій",
    "position": "Фінансовий менеджер",
    "picture": "./images/sergiy.png",
    "indexId": 3
  },
  {
    "id": 4,
    "name": "Соня",
    "position": "Дизайнерка",
    "picture": "./images/sonya.png",
    "indexId": 4
  },
  {
    "id": 5,
    "name": "Максим",
    "position": "Адміністратор майстерні",
    "picture": "./images/maksym.png",
    "indexId": 6
  },
  {
    "id": 6,
    "name": "Анна",
    "position": "Контентмейкерка",
    "picture": "./images/anna.png",
    "indexId": 5
  },
  {
    "id": 7,
    "name": "Євген",
    "position": "Веломайстер",
    "picture": "./images/evgen.png",
    "indexId": 8
  },
  {
    "id": 8,
    "name": "Олексій",
    "position": "Молодший спеціаліст",
    "picture": "./images/oleksiy.png",
    "indexId": 9
  },
  {
    "id": 9,
    "name": "Катя",
    "position": "Лаборантка",
    "picture": "./images/katya.png",
    "indexId": 7
  }
]
